pyTomoAO/__init__.py
pyTomoAO/atmosphereParametersClass.py
pyTomoAO/dmParametersClass.py
pyTomoAO/fitting.py
pyTomoAO/lgsAsterismParametersClass.py
pyTomoAO/lgsWfsParametersClass.py
pyTomoAO/tomographicReconstructor.py
pyTomoAO/tomographyParametersClass.py
pyTomoAO/tomographyUtilsCPU.py
pyTomoAO/tomographyUtilsGPU.py
pytomoao-1.0.1.dist-info/METADATA
pytomoao-1.0.1.dist-info/WHEEL
pytomoao-1.0.1.dist-info/top_level.txt
pytomoao-1.0.1.dist-info/RECORD
